is_git_repo_clean/__init__.py
is_git_repo_clean/check.py
is_git_repo_clean/cli.py
is_git_repo_clean/license.txt
is_git_repo_clean/meta.py
is_git_repo_clean/script.py
is_git_repo_clean/top_level.txt
is_git_repo_clean/utils.py
is_git_repo_clean-0.3.6.dist-info/entry_points.txt
is_git_repo_clean-0.3.6.dist-info/WHEEL
is_git_repo_clean-0.3.6.dist-info/METADATA
is_git_repo_clean-0.3.6.dist-info/RECORD
