Metadata-Version: 2.1
Name: is-git-repo-clean
Version: 0.3.6
Summary: A simple function to test whether your git repo is clean
Home-page: https://github.com/olsonpm/py_is-git-repo-clean
Author: Philip Olson
Author-email: philip.olson@pm.me
Requires-Python: >=3.7,<4.0
Classifier: Programming Language :: Python :: 3
Classifier: Programming Language :: Python :: 3.7
Project-URL: Repository, https://github.com/olsonpm/py_is-git-repo-clean
